Workbook

Sheet README
A1: PreCAS question bank — harvested 17 August 2026
A3: What this is | B3: Every pre-CAS / UKVI credibility interview question found by fetching 33 live web pages.
B4: Nothing here was invented. Each row carries the page it came from.
A6: Raw questions captured | B6: 534
A7: Unique question concepts after dedupe | B7: 401
A8: Backed by a university (.ac.uk) page | B8: 226
A9: Corroborated by 2 or more sources | B9: 67
A10: Corroborated by 3 or more sources | B10: 34
A11: Distinct source pages fetched | B11: 33
A13: Current bank in the product | B13: 26
A14: Questions per full mock | B14: 17
A16: How to use this sheet | B16: Work down the QUESTIONS tab. Set the Keep column to Y or N.
B17: Sort by Sources descending — the most-corroborated questions are the ones real interviews actually ask.
B18: Anything with 2+ sources and a .ac.uk tier is safe to ship without further checking.
A20: Important | B20: The question is the SAME for every university. What changes is the correct ANSWER.
B21: That is why there is no "university" column here. See the architecture note that came with this file.

Sheet QUESTIONS
A1: # | B1: Topic | C1: Question | D1: Sources | E1: Tiers | F1: Keep (Y/N) | G1: Source 1 | H1: URL 1 | I1: Source 2 | J1: URL 2 | K1: Other wordings seen
A2: 1 | B2: 3. Why this course | C2: Why did you choose this course? | D2: 9 | E2: agent, primary | G2: Birmingham City University — Credibility interviews | H2: https://www.bcu.ac.uk/international/preparing-for-the-uk/getting-your-visa/credibility-interviews | I2: Meridean Overseas Education Consultants — Pre-CAS Interview Preparation | J2: https://www.meridean.org/blog/pre-cas-interview | K2: Why did you choose your course?
A3: 2 | B3: 1. Why the UK | C3: Why do you want to study at University of Kent? | D3: 8 | E3: agent, primary | G3: Meridean Overseas Education Consultants — Pre-CAS Interview Preparation | H3: https://www.meridean.org/blog/pre-cas-interview | I3: Middlesex University — Preparing for your credibility interview | J3: https://www.mdx.ac.uk/international/student-visas/your-interview/ | K3: Why do you want to study in the UK?
A4: 3 | B4: 1. Why the UK | C4: Why have you chosen your course of study? | D4: 6 | E4: agent, primary | G4: NWC Education (Nepal) — Pre-CAS Interview Guide for Nepali Students | H4: https://nwc.education/pre-cas-interview-questions-preparation-for-nepali/ | I4: Northumbria University — Credibility interviews | J4: https://www.northumbria.ac.uk/study-at-northumbria/immigration/credibility-interviews/ | K4: What course have you chosen and why? | Why have you chosen this course? | Why have you chosen to study in the UK?
A5: 4 | B5: 3. Why this course | C5: How will your course be taught and assessed? | D5: 5 | E5: primary | G5: Coventry University — Credibility interviews | H5: https://www.coventry.ac.uk/international-students-hub/coming-to-the-uk/your-visa/credibility-interviews/ | I5: SOAS University of London — Credibility Interviews: Student Visa Applications | J5: https://www.soas.ac.uk/sites/default/files/2022-10/Credibility%20Interviews-%20student%20visa%20applications_0.pdf | K5: How is your course assessed?
A6: 5 | B6: 2. Why this university | C6: Which other colleges / universities have you considered? | D6: 5 | E6: agent, primary | G6: SOAS University of London — Credibility Interviews: Student Visa Applications | H6: https://www.soas.ac.uk/sites/default/files/2022-10/Credibility%20Interviews-%20student%20visa%20applications_0.pdf | I6: Sheffield Hallam University — Credibility interview practice questions (PDF) | J6: https://www.shu.ac.uk/-/media/home/international/files/int-credibility-interview-practice-qs.pdf | K6: Have you considered other colleges/Universities? | What other universities have you considered in the UK? | Which other colleges/universities have you considered?
A7: 6 | B7: 8. Accommodation & living | C7: How much will your accommodation cost? | D7: 4 | E7: primary | G7: Middlesex University — Preparing for your credibility interview | H7: https://www.mdx.ac.uk/international/student-visas/your-interview/ | I7: Oxford Brookes University — UKVI Credibility interviews | J7: https://www.brookes.ac.uk/students/isat/visas/student-visa/credibility-interviews
A8: 7 | B8: 6. Education history | C8: Why have you chosen this course and how does it relate to your previous study? | D8: 4 | E8: agent, primary | G8: Sheffield Hallam University — Credibility interview practice questions (PDF) | H8: https://www.shu.ac.uk/-/media/home/international/files/int-credibility-interview-practice-qs.pdf | I8: Staffordshire University — Guide to Credibility Interviews (PDF) | J8: https://www.staffs.ac.uk/international/pdf/guide-to-credibility-interviews.pdf | K8: Why did you choose this course and how does it relate to your previous study?
A9: 8 | B9: 6. Education history | C9: You have previously studied in the UK - why have you chosen to return? | D9: 4 | E9: agent, primary | G9: Birmingham City University — Credibility interviews | H9: https://www.bcu.ac.uk/international/preparing-for-the-uk/getting-your-visa/credibility-interviews | I9: Road To Abroad — Credibility Interview for UK: Sample Questions and Answers | J9: https://roadtoabroad.co.in/credibility-interview-for-uk/ | K9: You have previously studied in the UK – why have you chosen to return?
A10: 9 | B10: 4. Finance | C10: How will you fund your studies? | D10: 4 | E10: agent, primary | G10: Birmingham City University — Credibility interviews | H10: https://www.bcu.ac.uk/international/preparing-for-the-uk/getting-your-visa/credibility-interviews | I10: Road To Abroad — Credibility Interview for UK: Sample Questions and Answers | J10: https://roadtoabroad.co.in/credibility-interview-for-uk/
A11: 10 | B11: 5. Post-study plans | C11: How do your studies fit in with your career plans? | D11: 4 | E11: agent, primary | G11: Birmingham City University — Credibility interviews | H11: https://www.bcu.ac.uk/international/preparing-for-the-uk/getting-your-visa/credibility-interviews | I11: Road To Abroad — Credibility Interview for UK: Sample Questions and Answers | J11: https://roadtoabroad.co.in/credibility-interview-for-uk/ | K11: How do your studies fit into your career plans?
A12: 11 | B12: 7. Study gap | C12: You have had a (long) break in your studies, why are you returning to study now? | D12: 4 | E12: agent, primary | G12: Birmingham City University — Credibility interviews | H12: https://www.bcu.ac.uk/international/preparing-for-the-uk/getting-your-visa/credibility-interviews | I12: Road To Abroad — Credibility Interview for UK: Sample Questions and Answers | J12: https://roadtoabroad.co.in/credibility-interview-for-uk/ | K12: You have had a long break from your studies. Why are you returning to study now? | You have had a long break in your studies, why are you returning to study now?
A13: 12 | B13: 3. Why this course | C13: What modules will you study? | D13: 4 | E13: agent, primary | G13: Edwise Foundation (Nepal) — Pre-CAS Interview for Nepali Students | H13: https://edwisefoundation.com/pre-cas-interview-nepali-students/ | I13: Middlesex University — Preparing for your credibility interview | J13: https://www.mdx.ac.uk/international/student-visas/your-interview/
A14: 13 | B14: 3. Why this course | C14: How long does your course last? | D14: 4 | E14: agent, primary | G14: Middlesex University — Preparing for your credibility interview | H14: https://www.mdx.ac.uk/international/student-visas/your-interview/ | I14: Staffordshire University — Guide to Credibility Interviews (PDF) | J14: https://www.staffs.ac.uk/international/pdf/guide-to-credibility-interviews.pdf | K14: How long is the course? | How long is your course?
A15: 14 | B15: 3. Why this course | C15: What qualification will you receive when you graduate? | D15: 4 | E15: agent, primary | G15: Middlesex University — Preparing for your credibility interview | H15: https://www.mdx.ac.uk/international/student-visas/your-interview/ | I15: Staffordshire University — Guide to Credibility Interviews (PDF) | J15: https://www.staffs.ac.uk/international/pdf/guide-to-credibility-interviews.pdf | K15: What qualification will you receive?
A16: 15 | B16: 8. Accommodation & living | C16: Where will you live in the UK? | D16: 3 | E16: agent, primary | G16: Birmingham City University — Credibility interviews | H16: https://www.bcu.ac.uk/international/preparing-for-the-uk/getting-your-visa/credibility-interviews | I16: Edwise Foundation (Nepal) — Pre-CAS Interview for Nepali Students | J16: https://edwisefoundation.com/pre-cas-interview-nepali-students/ | K16: Where will you live?
A17: 16 | B17: 4. Finance | C17: Who will be financing the costs of your studies? | D17: 3 | E17: agent, primary | G17: Northumbria University — Credibility interviews | H17: https://www.northumbria.ac.uk/study-at-northumbria/immigration/credibility-interviews/ | I17: SOAS University of London — Credibility Interviews: Student Visa Applications | J17: https://www.soas.ac.uk/sites/default/files/2022-10/Credibility%20Interviews-%20student%20visa%20applications_0.pdf | K17: How are you financing your studies? | Who is financing your studies?
A18: 17 | B18: 4. Finance | C18: Do you know how you will you pay for your studies and living costs? | D18: 3 | E18: primary | G18: Middlesex University — Preparing for your credibility interview | H18: https://www.mdx.ac.uk/international/student-visas/your-interview/ | I18: University of Aberdeen — Credibility Interview | J18: https://www.abdn.ac.uk/study/international/credibility-interview-2559.php | K18: How will you pay for your studies and living costs? | How will you pay for your studies/living costs?
A19: 18 | B19: 4. Finance | C19: How are you funding your studies? | D19: 3 | E19: agent, primary | G19: Sheffield Hallam University — Credibility interview practice questions (PDF) | H19: https://www.shu.ac.uk/-/media/home/international/files/int-credibility-interview-practice-qs.pdf | I19: University of Aberdeen — Credibility Interview | J19: https://www.abdn.ac.uk/study/international/credibility-interview-2559.php | K19: Who is funding your studies?
A20: 19 | B20: 4. Finance | C20: If the costs of pursuing your course of study are higher in the UK than in your home country, why have you decided to incur the extra costs involved with studying in the UK? | D20: 3 | E20: agent, primary | G20: Road To Abroad — Credibility Interview for UK: Sample Questions and Answers | H20: https://roadtoabroad.co.in/credibility-interview-for-uk/ | I20: SOAS University of London — Credibility Interviews: Student Visa Applications | J20: https://www.soas.ac.uk/sites/default/files/2022-10/Credibility%20Interviews-%20student%20visa%20applications_0.pdf | K20: The costs of pursuing your course of study are higher in the UK than in your home country, why have you decided to incur the extra costs by studying in the UK?
A21: 20 | B21: 4. Finance | C21: What are your parents' annual income? | D21: 3 | E21: agent, primary | G21: Leverage Edu Learn — Pre-CAS Interview Prep: Commonly Asked Questions | H21: https://leverageedu.com/learn/visa-pre-cas-interview/ | I21: University of Reading — UKVI interview information for prospective students | J21: https://www.reading.ac.uk/essentials/International/Visa-and-immigration/credibility-interviews | K21: What is the annual income of your parents? | What is your parents' annual income?
A22: 21 | B22: 5. Post-study plans | C22: What are your future plans? | D22: 3 | E22: agent, primary | G22: Meridean Overseas Education Consultants — Pre-CAS Interview Preparation | H22: https://www.meridean.org/blog/pre-cas-interview | I22: University of Aberdeen — Credibility Interview | J22: https://www.abdn.ac.uk/study/international/credibility-interview-2559.php | K22: What are your future career plans?
A23: 22 | B23: 5. Post-study plans | C23: What is the relevance of the course to your future career path? | D23: 3 | E23: agent, primary | G23: Sheffield Hallam University — Credibility interview practice questions (PDF) | H23: https://www.shu.ac.uk/-/media/home/international/files/int-credibility-interview-practice-qs.pdf | I23: Staffordshire University — Guide to Credibility Interviews (PDF) | J23: https://www.staffs.ac.uk/international/pdf/guide-to-credibility-interviews.pdf
A24: 23 | B24: 5. Post-study plans | C24: Are you planning to stay in the UK on completion of your course to study for a higher award? | D24: 3 | E24: agent, primary | G24: Sheffield Hallam University — Credibility interview practice questions (PDF) | H24: https://www.shu.ac.uk/-/media/home/international/files/int-credibility-interview-practice-qs.pdf | I24: Staffordshire University — Guide to Credibility Interviews (PDF) | J24: https://www.staffs.ac.uk/international/pdf/guide-to-credibility-interviews.pdf | K24: After your course, are you planning to stay in the UK to study for a higher award? | Are you planning to stay in the UK on completion to study for a higher award?
A25: 24 | B25: 9. Visa & compliance | C25: Have you had any visa refusals in the past? | D25: 3 | E25: agent, primary | G25: Leverage Edu Learn — Pre-CAS Interview Prep: Commonly Asked Questions | H25: https://leverageedu.com/learn/visa-pre-cas-interview/ | I25: Meridean Overseas Education Consultants — Pre-CAS Interview Preparation | J25: https://www.meridean.org/blog/pre-cas-interview | K25: Do you have any past visa refusals? | Have you had any visa refusals?
A26: 25 | B26: 9. Visa & compliance | C26: Are you thinking of transferring to another institution on completion of your course? | D26: 3 | E26: agent, primary | G26: Sheffield Hallam University — Credibility interview practice questions (PDF) | H26: https://www.shu.ac.uk/-/media/home/international/files/int-credibility-interview-practice-qs.pdf | I26: Staffordshire University — Guide to Credibility Interviews (PDF) | J26: https://www.staffs.ac.uk/international/pdf/guide-to-credibility-interviews.pdf | K26: After your course, are you thinking of transferring to another institution? | Are you thinking of transferring to another institution on completing this course?
A27: 26 | B27: 7. Study gap | C27: Can you explain the gaps in your study/professional history? | D27: 3 | E27: agent, primary | G27: Sheffield Hallam University — Credibility interview practice questions (PDF) | H27: https://www.shu.ac.uk/-/media/home/international/files/int-credibility-interview-practice-qs.pdf | I27: Staffordshire University — Guide to Credibility Interviews (PDF) | J27: https://www.staffs.ac.uk/international/pdf/guide-to-credibility-interviews.pdf | K27: How do you explain the gaps in your study history? | How do you explain the gaps in your study/professional history?
A28: 27 | B28: 3. Why this course | C28: What other courses (if any) did you consider studying? | D28: 3 | E28: primary | G28: Middlesex University — Preparing for your credibility interview | H28: https://www.mdx.ac.uk/international/student-visas/your-interview/ | I28: University of Aberdeen — Credibility Interview | J28: https://www.abdn.ac.uk/study/international/credibility-interview-2559.php | K28: What other courses did you consider?
A29: 28 | B29: 3. Why this course | C29: How is your chosen course assessed? | D29: 3 | E29: agent, primary | G29: Sheffield Hallam University — Credibility interview practice questions (PDF) | H29: https://www.shu.ac.uk/-/media/home/international/files/int-credibility-interview-practice-qs.pdf | I29: Staffordshire University — Guide to Credibility Interviews (PDF) | J29: https://www.staffs.ac.uk/international/pdf/guide-to-credibility-interviews.pdf
A30: 29 | B30: 3. Why this course | C30: Does this course offer any professional recognition? | D30: 3 | E30: agent, primary | G30: Sheffield Hallam University — Credibility interview practice questions (PDF) | H30: https://www.shu.ac.uk/-/media/home/international/files/int-credibility-interview-practice-qs.pdf | I30: Staffordshire University — Guide to Credibility Interviews (PDF) | J30: https://www.staffs.ac.uk/international/pdf/guide-to-credibility-interviews.pdf
A31: 30 | B31: 1. Why the UK | C31: What are the benefits of studying in the UK compared to your home country or other countries that mean it is worth the cost to you? | D31: 3 | E31: primary | G31: Oxford Brookes University — UKVI Credibility interviews | H31: https://www.brookes.ac.uk/students/isat/visas/student-visa/credibility-interviews | I31: SOAS University of London — Credibility Interviews: Student Visa Applications | J31: https://www.soas.ac.uk/sites/default/files/2022-10/Credibility%20Interviews-%20student%20visa%20applications_0.pdf | K31: What are the benefits of studying in the UK compared to your home country or any other countries? | What are the benefits of studying in the UK compared to your home country?
A32: 31 | B32: 2. Why this university | C32: What other universities did you consider? Why? | D32: 3 | E32: primary | G32: Coventry University — Credibility interviews | H32: https://www.coventry.ac.uk/international-students-hub/coming-to-the-uk/your-visa/credibility-interviews/ | I32: University of Bradford — Credibility checks: Student visas | J32: https://www.bradford.ac.uk/international/support/visa-support/student-visas/credibility-checks/ | K32: Which other Universities did you consider? | Which other universities did you consider?
A33: 32 | B33: 2. Why this university | C33: How did you find out about it? | D33: 3 | E33: agent, primary | G33: Sheffield Hallam University — Credibility interview practice questions (PDF) | H33: https://www.shu.ac.uk/-/media/home/international/files/int-credibility-interview-practice-qs.pdf | I33: Staffordshire University — Guide to Credibility Interviews (PDF) | J33: https://www.staffs.ac.uk/international/pdf/guide-to-credibility-interviews.pdf
A34: 33 | B34: 2. Why this university | C34: Do you know anyone else who has already studied there? | D34: 3 | E34: agent, primary | G34: Sheffield Hallam University — Credibility interview practice questions (PDF) | H34: https://www.shu.ac.uk/-/media/home/international/files/int-credibility-interview-practice-qs.pdf | I34: Staffordshire University — Guide to Credibility Interviews (PDF) | J34: https://www.staffs.ac.uk/international/pdf/guide-to-credibility-interviews.pdf | K34: Do you know anyone who has already studied there?
A35: 34 | B35: 2. Why this university | C35: Why did you choose Birmingham City University (BCU)? | D35: 3 | E35: agent, primary | G35: Birmingham City University — Credibility interviews | H35: https://www.bcu.ac.uk/international/preparing-for-the-uk/getting-your-visa/credibility-interviews | I35: Meridean Overseas Education Consultants — Pre-CAS Interview Preparation | J35: https://www.meridean.org/blog/pre-cas-interview | K35: Why did you choose Roehampton University? | Why did you choose this university?
A36: 35 | B36: 8. Accommodation & living | C36: Where do you plan to live during your studies at Northumbria University? | D36: 2 | E36: primary | G36: Northumbria University — Credibility interviews | H36: https://www.northumbria.ac.uk/study-at-northumbria/immigration/credibility-interviews/ | I36: Oxford Brookes University — UKVI Credibility interviews | J36: https://www.brookes.ac.uk/students/isat/visas/student-visa/credibility-interviews | K36: Where do you plan to live during your studies?
A37: 36 | B37: 6. Education history | C37: Have you studied abroad previously? | D37: 2 | E37: primary | G37: University of Hertfordshire — Sponsorship interview | H37: https://www.herts.ac.uk/international/apply/offer-holder-guidance/sponsorship-interview | I37: University of Lincoln — Pre-CAS Interview | Information for Offer Holders | J37: https://www.lincoln.ac.uk/studywithus/internationalstudents/informationforofferholders/pre-casinterview/ | K37: What have you studied previously?
A38: 37 | B38: 4. Finance | C38: How much are the tuition fees? | D38: 2 | E38: primary | G38: Middlesex University — Preparing for your credibility interview | H38: https://www.mdx.ac.uk/international/student-visas/your-interview/ | I38: University of Aberdeen — Credibility Interview | J38: https://www.abdn.ac.uk/study/international/credibility-interview-2559.php
A39: 38 | B39: 4. Finance | C39: Are you able to pay your tuition fees in full up front? | D39: 2 | E39: agent, primary | G39: SOAS University of London — Credibility Interviews: Student Visa Applications | H39: https://www.soas.ac.uk/sites/default/files/2022-10/Credibility%20Interviews-%20student%20visa%20applications_0.pdf | I39: Staffordshire University — Guide to Credibility Interviews (PDF) | J39: https://www.staffs.ac.uk/international/pdf/guide-to-credibility-interviews.pdf | K39: Would you be able to pay your tuition fees in full up front?
A40: 39 | B40: 4. Finance | C40: Have you checked the University refund policy? | D40: 2 | E40: agent, primary | G40: SOAS University of London — Credibility Interviews: Student Visa Applications | H40: https://www.soas.ac.uk/sites/default/files/2022-10/Credibility%20Interviews-%20student%20visa%20applications_0.pdf | I40: Staffordshire University — Guide to Credibility Interviews (PDF) | J40: https://www.staffs.ac.uk/international/pdf/guide-to-credibility-interviews.pdf | K40: Have you checked the refund policy?
A41: 40 | B41: 4. Finance | C41: How will you finance your studies (fees and living costs in the UK)? | D41: 2 | E41: primary | G41: University of Reading — UKVI interview information for prospective students | H41: https://www.reading.ac.uk/essentials/International/Visa-and-immigration/credibility-interviews | I41: University of Westminster — Credibility interviews | J41: https://www.westminster.ac.uk/international/visas-and-advice/visas/student-visa/credibility-interviews
A42: 41 | B42: 4. Finance | C42: How will they manage to pay for your studies in the UK and their own regular living expenses? | D42: 2 | E42: primary | G42: University of Reading — UKVI interview information for prospective students | H42: https://www.reading.ac.uk/essentials/International/Visa-and-immigration/credibility-interviews | I42: University of Westminster — Credibility interviews | J42: https://www.westminster.ac.uk/international/visas-and-advice/visas/student-visa/credibility-interviews | K42: How will they manage to pay for your studies in the UK and their own regular living expenses
A43: 42 | B43: 4. Finance | C43: How much money will you need per month for living expenses? | D43: 2 | E43: primary | G43: University of Reading — UKVI interview information for prospective students | H43: https://www.reading.ac.uk/essentials/International/Visa-and-immigration/credibility-interviews | I43: University of Westminster — Credibility interviews | J43: https://www.westminster.ac.uk/international/visas-and-advice/visas/student-visa/credibility-interviews
A44: 43 | B44: 4. Finance | C44: Will you have access to this money for the whole of your studies in the UK? | D44: 2 | E44: primary | G44: University of Reading — UKVI interview information for prospective students | H44: https://www.reading.ac.uk/essentials/International/Visa-and-immigration/credibility-interviews | I44: University of Westminster — Credibility interviews | J44: https://www.westminster.ac.uk/international/visas-and-advice/visas/student-visa/credibility-interviews
A45: 44 | B45: 4. Finance | C45: If you are funding your studies in the UK yourself, how do you see this investment being worth the cost? | D45: 2 | E45: primary | G45: University of Reading — UKVI interview information for prospective students | H45: https://www.reading.ac.uk/essentials/International/Visa-and-immigration/credibility-interviews | I45: University of Westminster — Credibility interviews | J45: https://www.westminster.ac.uk/international/visas-and-advice/visas/student-visa/credibility-interviews
A46: 45 | B46: 5. Post-study plans | C46: What are your future career goals, and how will this course help you achieve them? | D46: 2 | E46: primary | G46: Northumbria University — Credibility interviews | H46: https://www.northumbria.ac.uk/study-at-northumbria/immigration/credibility-interviews/ | I46: Oxford Brookes University — UKVI Credibility interviews | J46: https://www.brookes.ac.uk/students/isat/visas/student-visa/credibility-interviews | K46: How will the course help you with your future career goals?
A47: 46 | B47: 5. Post-study plans | C47: How relevant is this course to your future career plans? | D47: 2 | E47: agent, primary | G47: SOAS University of London — Credibility Interviews: Student Visa Applications | H47: https://www.soas.ac.uk/sites/default/files/2022-10/Credibility%20Interviews-%20student%20visa%20applications_0.pdf | I47: UKVisa.blog — UK Student Visa Interview 2025: Best Tips to Show Credibility | J47: https://ukvisa.blog/uk-student-visa-interview/ | K47: How is this course relevant to your future plans?
A48: 47 | B48: 5. Post-study plans | C48: What do you plan to do after completing your course? | D48: 2 | E48: primary | G48: Bournemouth University — Credibility interviews: information for international applicants | H48: https://www.bournemouth.ac.uk/students/help-advice/international-students/immigration-visas/student-route-visa/visa-application-credibility-interviews | I48: SOAS University of London — Credibility Interviews: Student Visa Applications | J48: https://www.soas.ac.uk/sites/default/files/2022-10/Credibility%20Interviews-%20student%20visa%20applications_0.pdf | K48: What will you do after completing your course?
A49: 48 | B49: 10. Identity & personal | C49: Can you please introduce yourself? | D49: 2 | E49: agent | G49: Edwise Foundation (Nepal) — Pre-CAS Interview for Nepali Students | H49: https://edwisefoundation.com/pre-cas-interview-nepali-students/ | I49: Leverage Edu Learn — Pre-CAS Interview Prep: Commonly Asked Questions | J49: https://leverageedu.com/learn/visa-pre-cas-interview/ | K49: Introduce yourself.
A50: 49 | B50: 9. Visa & compliance | C50: Do you plan to work part-time during your studies? | D50: 2 | E50: agent, primary | G50: Oxford Brookes University — UKVI Credibility interviews | H50: https://www.brookes.ac.uk/students/isat/visas/student-visa/credibility-interviews | I50: UKVisa.blog — UK Student Visa Interview 2025: Best Tips to Show Credibility | J50: https://ukvisa.blog/uk-student-visa-interview/ | K50: Do you plan to work part-time in the UK?
A51: 50 | B51: 9. Visa & compliance | C51: Are you planning to work while you are in the UK? | D51: 2 | E51: primary | G51: Middlesex University — Preparing for your credibility interview | H51: https://www.mdx.ac.uk/international/student-visas/your-interview/ | I51: University of Aberdeen — Credibility Interview | J51: https://www.abdn.ac.uk/study/international/credibility-interview-2559.php
A52: 51 | B52: 9. Visa & compliance | C52: Do you plan to work in the UK? | D52: 2 | E52: agent, primary | G52: Birmingham City University — Credibility interviews | H52: https://www.bcu.ac.uk/international/preparing-for-the-uk/getting-your-visa/credibility-interviews | I52: Road To Abroad — Credibility Interview for UK: Sample Questions and Answers | J52: https://roadtoabroad.co.in/credibility-interview-for-uk/
A53: 52 | B53: 9. Visa & compliance | C53: Have you had any visas for other countries? | D53: 2 | E53: agent, primary | G53: Staffordshire University — Guide to Credibility Interviews (PDF) | H53: https://www.staffs.ac.uk/international/pdf/guide-to-credibility-interviews.pdf | I53: University of Portsmouth — Credibility interviews | J53: https://myport.port.ac.uk/study/international-students/visa-advice/credibility-interviews | K53: Have you had any visas for any other countries?
A54: 53 | B54: 9. Visa & compliance | C54: Have you ever visited the UK before? | D54: 2 | E54: agent, primary | G54: UKVisa.blog — UK Student Visa Interview 2025: Best Tips to Show Credibility | H54: https://ukvisa.blog/uk-student-visa-interview/ | I54: University of Bradford — Credibility checks: Student visas | J54: https://www.bradford.ac.uk/international/support/visa-support/student-visas/credibility-checks/
A55: 54 | B55: 9. Visa & compliance | C55: Have you ever had a visa refusal for the UK or any other country? | D55: 2 | E55: agent, primary | G55: Optimus Global Education — UK Pre-CAS Interview 2026 | H55: https://www.optimusglobaledu.com/blogs/uk-pre-cas-interview-guide-2026 | I55: University of Bradford — Credibility checks: Student visas | J55: https://www.bradford.ac.uk/international/support/visa-support/student-visas/credibility-checks/
A56: 55 | B56: 9. Visa & compliance | C56: Do you know how many hours you are allowed to work in the UK? | D56: 2 | E56: agent | G56: AEC Overseas — Top UK Student Visa Interview Questions and Answers | H56: https://www.aecoverseas.com/blog/uk-student-visa-interview-questions-answers/ | I56: Staffordshire University — Guide to Credibility Interviews (PDF) | J56: https://www.staffs.ac.uk/international/pdf/guide-to-credibility-interviews.pdf | K56: Do you know how many hours you are allowed to work?
A57: 56 | B57: 3. Why this course | C57: How will you be assessed? | D57: 2 | E57: agent, primary | G57: Edwise Foundation (Nepal) — Pre-CAS Interview for Nepali Students | H57: https://edwisefoundation.com/pre-cas-interview-nepali-students/ | I57: Middlesex University — Preparing for your credibility interview | J57: https://www.mdx.ac.uk/international/student-visas/your-interview/ | K57: How is it assessed?
A58: 57 | B58: 3. Why this course | C58: What do you know about the structure of your course? | D58: 2 | E58: primary | G58: Bournemouth University — Credibility interviews: information for international applicants | H58: https://www.bournemouth.ac.uk/students/help-advice/international-students/immigration-visas/student-route-visa/visa-application-credibility-interviews | I58: SOAS University of London — Credibility Interviews: Student Visa Applications | J58: https://www.soas.ac.uk/sites/default/files/2022-10/Credibility%20Interviews-%20student%20visa%20applications_0.pdf | K58: What is the structure of the course?
A59: 58 | B59: 3. Why this course | C59: Do you know what level your course is at? | D59: 2 | E59: agent, primary | G59: Staffordshire University — Guide to Credibility Interviews (PDF) | H59: https://www.staffs.ac.uk/international/pdf/guide-to-credibility-interviews.pdf | I59: University of Reading — UKVI interview information for prospective students | J59: https://www.reading.ac.uk/essentials/International/Visa-and-immigration/credibility-interviews
A60: 59 | B60: 3. Why this course | C60: Did you consider any other course? | D60: 2 | E60: agent, primary | G60: Staffordshire University — Guide to Credibility Interviews (PDF) | H60: https://www.staffs.ac.uk/international/pdf/guide-to-credibility-interviews.pdf | I60: University of Reading — UKVI interview information for prospective students | J60: https://www.reading.ac.uk/essentials/International/Visa-and-immigration/credibility-interviews
A61: 60 | B61: 1. Why the UK | C61: What motivated you to choose the UK as your study destination? | D61: 2 | E61: agent, primary | G61: Bournemouth University — Credibility interviews: information for international applicants | H61: https://www.bournemouth.ac.uk/students/help-advice/international-students/immigration-visas/student-route-visa/visa-application-credibility-interviews | I61: University of Plymouth — UKVI credibility interviews | J61: https://www.plymouth.ac.uk/services/international-student-advice/ukvi-credibility-interviews
A62: 61 | B62: 1. Why the UK | C62: What are the benefits of studying in the UK compared to your home country or USA/Canada/Australia etc.? | D62: 2 | E62: agent, primary | G62: Sheffield Hallam University — Credibility interview practice questions (PDF) | H62: https://www.shu.ac.uk/-/media/home/international/files/int-credibility-interview-practice-qs.pdf | I62: Staffordshire University — Guide to Credibility Interviews (PDF) | J62: https://www.staffs.ac.uk/international/pdf/guide-to-credibility-interviews.pdf | K62: What are the benefits of studying in the UK compared to your home country or USA/Canada/Australia etc?
A63: 62 | B63: 1. Why the UK | C63: Why did you choose to study in the UK? | D63: 2 | E63: agent, primary | G63: NWC Education (Nepal) — Pre-CAS Interview Guide for Nepali Students | H63: https://nwc.education/pre-cas-interview-questions-preparation-for-nepali/ | I63: University of Gloucestershire — Credibility interviews (Knowledge Base) | J63: https://www.glos.ac.uk/information/knowledge-base/credibility-interviews/ | K63: Why did you choose this field of study?
A64: 63 | B64: 2. Why this university | C64: Why did you choose University of Reading over other universities? | D64: 2 | E64: primary | G64: University of Lincoln — Pre-CAS Interview | Information for Offer Holders | H64: https://www.lincoln.ac.uk/studywithus/internationalstudents/informationforofferholders/pre-casinterview/ | I64: University of Reading — UKVI interview information for prospective students | J64: https://www.reading.ac.uk/essentials/International/Visa-and-immigration/credibility-interviews | K64: Why did you choose the UK? | Why did you choose the University of Lincoln?
A65: 64 | B65: 2. Why this university | C65: Which other institutions did you consider? | D65: 2 | E65: primary | G65: Middlesex University — Preparing for your credibility interview | H65: https://www.mdx.ac.uk/international/student-visas/your-interview/ | I65: University of Aberdeen — Credibility Interview | J65: https://www.abdn.ac.uk/study/international/credibility-interview-2559.php | K65: What other institutions did you consider?
A66: 65 | B66: 2. Why this university | C66: Where is the college / university? | D66: 2 | E66: agent, primary | G66: Sheffield Hallam University — Credibility interview practice questions (PDF) | H66: https://www.shu.ac.uk/-/media/home/international/files/int-credibility-interview-practice-qs.pdf | I66: Staffordshire University — Guide to Credibility Interviews (PDF) | J66: https://www.staffs.ac.uk/international/pdf/guide-to-credibility-interviews.pdf | K66: Where is the college/university? | Why did you choose this university/college?
A67: 66 | B67: 2. Why this university | C67: Do you know roughly how large the college / university is? | D67: 2 | E67: agent, primary | G67: Sheffield Hallam University — Credibility interview practice questions (PDF) | H67: https://www.shu.ac.uk/-/media/home/international/files/int-credibility-interview-practice-qs.pdf | I67: Staffordshire University — Guide to Credibility Interviews (PDF) | J67: https://www.staffs.ac.uk/international/pdf/guide-to-credibility-interviews.pdf | K67: Do you know roughly how large the college/university is?
A68: 67 | B68: 2. Why this university | C68: What facilities are you expecting at the college/university? | D68: 2 | E68: agent, primary | G68: Sheffield Hallam University — Credibility interview practice questions (PDF) | H68: https://www.shu.ac.uk/-/media/home/international/files/int-credibility-interview-practice-qs.pdf | I68: Staffordshire University — Guide to Credibility Interviews (PDF) | J68: https://www.staffs.ac.uk/international/pdf/guide-to-credibility-interviews.pdf
A69: 68 | B69: 8. Accommodation & living | C69: What research have you undertaken regarding accommodation options? | D69: 1 | E69: primary | G69: University of Lincoln — Pre-CAS Interview | Information for Offer Holders | H69: https://www.lincoln.ac.uk/studywithus/internationalstudents/informationforofferholders/pre-casinterview/
A70: 69 | B70: 8. Accommodation & living | C70: Do you plan to live on or off campus? Why? | D70: 1 | E70: primary | G70: University of Lincoln — Pre-CAS Interview | Information for Offer Holders | H70: https://www.lincoln.ac.uk/studywithus/internationalstudents/informationforofferholders/pre-casinterview/
A71: 70 | B71: 8. Accommodation & living | C71: How far is your preferred accommodation from the University? | D71: 1 | E71: primary | G71: University of Lincoln — Pre-CAS Interview | Information for Offer Holders | H71: https://www.lincoln.ac.uk/studywithus/internationalstudents/informationforofferholders/pre-casinterview/
A72: 71 | B72: 8. Accommodation & living | C72: How will you travel to classes? | D72: 1 | E72: primary | G72: University of Lincoln — Pre-CAS Interview | Information for Offer Holders | H72: https://www.lincoln.ac.uk/studywithus/internationalstudents/informationforofferholders/pre-casinterview/
A73: 72 | B73: 8. Accommodation & living | C73: What do you know about Oxford as a place to live and study? | D73: 1 | E73: primary | G73: Oxford Brookes University — UKVI Credibility interviews | H73: https://www.brookes.ac.uk/students/isat/visas/student-visa/credibility-interviews
A74: 73 | B74: 8. Accommodation & living | C74: How will you travel to and from the university? | D74: 1 | E74: primary | G74: Oxford Brookes University — UKVI Credibility interviews | H74: https://www.brookes.ac.uk/students/isat/visas/student-visa/credibility-interviews
A75: 74 | B75: 8. Accommodation & living | C75: Where do you plan to live while studying at University of Kent? | D75: 1 | E75: primary | G75: University of Kent — Credibility Interviews | H75: https://www.kent.ac.uk/international/credibility-interviews
A76: 75 | B76: 8. Accommodation & living | C76: Where will you live and how far will this be from campus? | D76: 1 | E76: primary | G76: University of Aberdeen — Credibility Interview | H76: https://www.abdn.ac.uk/study/international/credibility-interview-2559.php
A77: 76 | B77: 8. Accommodation & living | C77: How will you travel to campus each day and the bus routes? | D77: 1 | E77: primary | G77: University of Aberdeen — Credibility Interview | H77: https://www.abdn.ac.uk/study/international/credibility-interview-2559.php
A78: 77 | B78: 8. Accommodation & living | C78: Have you found accommodation? Do you know the costs of accommodation in London? | D78: 1 | E78: primary | G78: SOAS University of London — Credibility Interviews: Student Visa Applications | H78: https://www.soas.ac.uk/sites/default/files/2022-10/Credibility%20Interviews-%20student%20visa%20applications_0.pdf
A79: 78 | B79: 8. Accommodation & living | C79: Where will you live in London, how far is it from the campus you will study on, and why do you want to live there? | D79: 1 | E79: primary | G79: University of Westminster — Credibility interviews | H79: https://www.westminster.ac.uk/international/visas-and-advice/visas/student-visa/credibility-interviews
A80: 79 | B80: 8. Accommodation & living | C80: How will you travel from your accommodation to the University? | D80: 1 | E80: primary | G80: University of Westminster — Credibility interviews | H80: https://www.westminster.ac.uk/international/visas-and-advice/visas/student-visa/credibility-interviews
... A365: 364 | B365: 2. Why this university | C365: Why did you decide to study at Northumbria University? | D365: 1 | E365: primary | G365: Northumbria University — Credibility interviews | H365: https://www.northumbria.ac.uk/study-at-northumbria/immigration/credibility-interviews/
A366: 365 | B366: 2. Why this university | C366: Why did you choose the University of Aberdeen? | D366: 1 | E366: primary | G366: University of Aberdeen — Credibility Interview | H366: https://www.abdn.ac.uk/study/international/credibility-interview-2559.php | K366: Why did you choose Aberdeen?
A367: 366 | B367: 2. Why this university | C367: Where is the University of Aberdeen? | D367: 1 | E367: primary | G367: University of Aberdeen — Credibility Interview | H367: https://www.abdn.ac.uk/study/international/credibility-interview-2559.php
A368: 367 | B368: 2. Why this university | C368: How big is the University of Aberdeen? | D368: 1 | E368: primary | G368: University of Aberdeen — Credibility Interview | H368: https://www.abdn.ac.uk/study/international/credibility-interview-2559.php
A369: 368 | B369: 2. Why this university | C369: Why did you choose your institution? | D369: 1 | E369: primary | G369: Middlesex University — Preparing for your credibility interview | H369: https://www.mdx.ac.uk/international/student-visas/your-interview/
A370: 369 | B370: 2. Why this university | C370: Where is your institution? | D370: 1 | E370: primary | G370: Middlesex University — Preparing for your credibility interview | H370: https://www.mdx.ac.uk/international/student-visas/your-interview/
A371: 370 | B371: 2. Why this university | C371: How big is your institution? | D371: 1 | E371: primary | G371: Middlesex University — Preparing for your credibility interview | H371: https://www.mdx.ac.uk/international/student-visas/your-interview/
A372: 371 | B372: 2. Why this university | C372: Why did you choose this university (i.e. SOAS) to study in the UK? | D372: 1 | E372: primary | G372: SOAS University of London — Credibility Interviews: Student Visa Applications | H372: https://www.soas.ac.uk/sites/default/files/2022-10/Credibility%20Interviews-%20student%20visa%20applications_0.pdf
A373: 372 | B373: 2. Why this university | C373: Did you consider any other universities and what made you decide on this university? | D373: 1 | E373: primary | G373: University of Westminster — Credibility interviews | H373: https://www.westminster.ac.uk/international/visas-and-advice/visas/student-visa/credibility-interviews
A374: 373 | B374: 2. Why this university | C374: Describe the University campus – which campus is your course on? | D374: 1 | E374: primary | G374: University of Westminster — Credibility interviews | H374: https://www.westminster.ac.uk/international/visas-and-advice/visas/student-visa/credibility-interviews
A375: 374 | B375: 2. Why this university | C375: Can you describe the facilities at the University? | D375: 1 | E375: primary | G375: University of Westminster — Credibility interviews | H375: https://www.westminster.ac.uk/international/visas-and-advice/visas/student-visa/credibility-interviews
A376: 375 | B376: 2. Why this university | C376: Do you know how large the university is? | D376: 1 | E376: primary | G376: University of Reading — UKVI interview information for prospective students | H376: https://www.reading.ac.uk/essentials/International/Visa-and-immigration/credibility-interviews
A377: 376 | B377: 2. Why this university | C377: What facilities do you expect there to be at University of Reading? | D377: 1 | E377: primary | G377: University of Reading — UKVI interview information for prospective students | H377: https://www.reading.ac.uk/essentials/International/Visa-and-immigration/credibility-interviews
A378: 377 | B378: 2. Why this university | C378: What made Bournemouth University stand out compared to other UK universities? | D378: 1 | E378: primary | G378: Bournemouth University — Credibility interviews: information for international applicants | H378: https://www.bournemouth.ac.uk/students/help-advice/international-students/immigration-visas/student-route-visa/visa-application-credibility-interviews
... A402: 401 | B402: 2. Why this university | C402: Where is your university? | D402: 1 | E402: agent | G402: Global Pathways — UK Student Visa Interview Questions (2026 Guide) | H402: https://www.globalpathways.co.uk/uk-student-visa-interview-questions/

Sheet BY TOPIC
A1: Topic | B1: Questions found | C1: Questions per mock (target) | D1: Have enough?
A2: 1. Why the UK | B2: =COUNTIF(QUESTIONS!$B$2:$B$402,A2) -> 30 | C2: 2 | D2: =IF(B2>=C2*8,"yes","needs more") -> yes
A3: 10. Identity & personal | B3: =COUNTIF(QUESTIONS!$B$2:$B$402,A3) -> 11 | C3: 1 | D3: =IF(B3>=C3*8,"yes","needs more") -> yes
A4: 11. English ability | B4: =COUNTIF(QUESTIONS!$B$2:$B$402,A4) -> 4 | C4: 1 | D4: =IF(B4>=C4*8,"yes","needs more") -> needs more
A5: 12. Other | B5: =COUNTIF(QUESTIONS!$B$2:$B$402,A5) -> 5 | C5: 0 | D5: =IF(B5>=C5*8,"yes","needs more") -> yes
A6: 2. Why this university | B6: =COUNTIF(QUESTIONS!$B$2:$B$402,A6) -> 54 | C6: 3 | D6: =IF(B6>=C6*8,"yes","needs more") -> yes
A7: 3. Why this course | B7: =COUNTIF(QUESTIONS!$B$2:$B$402,A7) -> 48 | C7: 3 | D7: =IF(B7>=C7*8,"yes","needs more") -> yes
A8: 4. Finance | B8: =COUNTIF(QUESTIONS!$B$2:$B$402,A8) -> 82 | C8: 3 | D8: =IF(B8>=C8*8,"yes","needs more") -> yes
A9: 5. Post-study plans | B9: =COUNTIF(QUESTIONS!$B$2:$B$402,A9) -> 44 | C9: 2 | D9: =IF(B9>=C9*8,"yes","needs more") -> yes
A10: 6. Education history | B10: =COUNTIF(QUESTIONS!$B$2:$B$402,A10) -> 21 | C10: 1 | D10: =IF(B10>=C10*8,"yes","needs more") -> yes
A11: 7. Study gap | B11: =COUNTIF(QUESTIONS!$B$2:$B$402,A11) -> 17 | C11: 1 | D11: =IF(B11>=C11*8,"yes","needs more") -> yes
A12: 8. Accommodation & living | B12: =COUNTIF(QUESTIONS!$B$2:$B$402,A12) -> 37 | C12: 1 | D12: =IF(B12>=C12*8,"yes","needs more") -> yes
A13: 9. Visa & compliance | B13: =COUNTIF(QUESTIONS!$B$2:$B$402,A13) -> 48 | C13: 1 | D13: =IF(B13>=C13*8,"yes","needs more") -> yes
A14: TOTAL | B14: =SUM(B2:B13) -> 401 | C14: =SUM(C2:C13) -> 19
A16: Rule of thumb: a student should not meet a repeat before mock 3.
A17: So each topic needs about 8x the number of slots it fills in one mock.

Sheet SOURCES
A1: Source page | B1: URL | C1: Tier | D1: Questions from it
A2: The Mentors Circle — UK Student Visa Interview Questions 2026: India Guide | B2: https://thementorscircle.com/blogs/post/uk-student-visa-interview-questions-2026-indian-students-guide/ | C2: agent | D2: 48
A3: Staffordshire University — Guide to Credibility Interviews (PDF) | B3: https://www.staffs.ac.uk/international/pdf/guide-to-credibility-interviews.pdf | C3: agent | D3: 42
A4: University of Aberdeen — Credibility Interview | B4: https://www.abdn.ac.uk/study/international/credibility-interview-2559.php | C4: primary | D4: 36
A5: University of Reading — UKVI interview information for prospective students | B5: https://www.reading.ac.uk/essentials/International/Visa-and-immigration/credibility-interviews | C5: primary | D5: 32
A6: Oxford Brookes University — UKVI Credibility interviews | B6: https://www.brookes.ac.uk/students/isat/visas/student-visa/credibility-interviews | C6: primary | D6: 28
A7: Sheffield Hallam University — Credibility interview practice questions (PDF) | B7: https://www.shu.ac.uk/-/media/home/international/files/int-credibility-interview-practice-qs.pdf | C7: primary | D7: 28
A8: NWC Education (Nepal) — Pre-CAS Interview Guide for Nepali Students | B8: https://nwc.education/pre-cas-interview-questions-preparation-for-nepali/ | C8: agent | D8: 27
A9: SOAS University of London — Credibility Interviews: Student Visa Applications | B9: https://www.soas.ac.uk/sites/default/files/2022-10/Credibility%20Interviews-%20student%20visa%20applications_0.pdf | C9: primary | D9: 23
A10: University of Bradford — Credibility checks: Student visas | B10: https://www.bradford.ac.uk/international/support/visa-support/student-visas/credibility-checks/ | C10: primary | D10: 21
A11: University of Westminster — Credibility interviews | B11: https://www.westminster.ac.uk/international/visas-and-advice/visas/student-visa/credibility-interviews | C11: primary | D11: 20
A12: Bournemouth University — Credibility interviews: information for international applicants | B12: https://www.bournemouth.ac.uk/students/help-advice/international-students/immigration-visas/student-route-visa/visa-application-credibility-interviews | C12: primary | D12: 19
A13: Middlesex University — Preparing for your credibility interview | B13: https://www.mdx.ac.uk/international/student-visas/your-interview/ | C13: primary | D13: 18
... A34: Rajveer Chahal — UKVI Credibility Interview Questions & Answers 2026 | B34: https://rajveerchahal.com/ukvi-credibility-interview-questions-answers-2026/ | C34: agent | D34: 2
